{
  "generator-jhipster": {
    "promptValues": {
      "packageName": "com.eikesi.demo.gateway",
      "nativeLanguage": "zh-cn"
    },
    "jhipsterVersion": "5.1.0",
    "applicationType": "gateway",
    "baseName": "demoGateway",
    "packageName": "com.eikesi.demo.gateway",
    "packageFolder": "com/eikesi/demo/gateway",
    "serverPort": "80000",
    "authenticationType": "uaa",
    "uaaBaseName": "uaaServer",
    "cacheProvider": "hazelcast",
    "enableHibernateCache": true,
    "websocket": false,
    "databaseType": "sql",
    "devDatabaseType": "mysql",
    "prodDatabaseType": "mysql",
    "searchEngine": "elasticsearch",
    "messageBroker": "kafka",
    "serviceDiscoveryType": "eureka",
    "buildTool": "maven",
    "enableSwaggerCodegen": true,
    "clientFramework": "angularX",
    "useSass": true,
    "clientPackageManager": "yarn",
    "testFrameworks": [
      "gatling",
      "protractor"
    ],
    "jhiPrefix": "jhi",
    "otherModules": [
      {
        "name": "generator-jhipster-nav-element",
        "version": "2.0.2"
      },
      {
        "name": "generator-jhipster-docker",
        "version": "2.5.0"
      },
      {
        "name": "generator-jhipster-audit-helper",
        "version": "1.0.3"
      },
      {
        "name": "generator-jhipster-uaa-security-authority",
        "version": "1.0.1"
      },
      {
        "name": "generator-jhipster-obfuscation-at-rest",
        "version": "0.3.0"
      },
      {
        "name": "generator-jhipster-feign-client",
        "version": "1.0.6"
      },
      {
        "name": "generator-jhipster-cockroachdb",
        "version": "0.0.10"
      },
      {
        "name": "generator-jhipster-file2url",
        "version": "0.0.0"
      }
    ],
    "enableTranslation": true,
    "nativeLanguage": "zh-cn",
    "languages": [
      "zh-cn",
      "zh-tw",
      "en"
    ]
  }
}